{
  "2012": [
    {
      "g": 141,
      "montant": 200
    },
    {
      "g": 142,
      "montant": 200
    },
    {
      "g": 143,
      "montant": 200
    },
    {
      "g": 144,
      "montant": 200
    },
    {
      "g": 145,
      "montant": 200
    },
    {
      "g": 146,
      "montant": 200
    },
    {
      "g": 147,
      "montant": 200
    },
    {
      "g": 148,
      "montant": 200
    },
    {
      "g": 149,
      "montant": 200
    },
    {
      "g": 150,
      "montant": 200
    },
    {
      "g": 151,
      "montant": 500
    },
    {
      "g": 152,
      "montant": 500
    },
    {
      "g": 153,
      "montant": 500
    },
    {
      "g": 154,
      "montant": 500
    },
    {
      "g": 155,
      "montant": 500
    },
    {
      "g": 156,
      "montant": 750
    },
    {
      "g": 157,
      "montant": 750
    },
    {
      "g": 158,
      "montant": 750
    },
    {
      "g": 159,
      "montant": 750
    },
    {
      "g": 160,
      "montant": 750
    },
    {
      "g": 161,
      "montant": 750
    },
    {
      "g": 162,
      "montant": 750
    },
    {
      "g": 163,
      "montant": 750
    },
    {
      "g": 164,
      "montant": 750
    },
    {
      "g": 165,
      "montant": 750
    },
    {
      "g": 166,
      "montant": 750
    },
    {
      "g": 167,
      "montant": 750
    },
    {
      "g": 168,
      "montant": 750
    },
    {
      "g": 169,
      "montant": 750
    },
    {
      "g": 170,
      "montant": 750
    },
    {
      "g": 171,
      "montant": 750
    },
    {
      "g": 172,
      "montant": 750
    },
    {
      "g": 173,
      "montant": 750
    },
    {
      "g": 174,
      "montant": 750
    },
    {
      "g": 175,
      "montant": 750
    },
    {
      "g": 176,
      "montant": 750
    },
    {
      "g": 177,
      "montant": 750
    },
    {
      "g": 178,
      "montant": 750
    },
    {
      "g": 179,
      "montant": 750
    },
    {
      "g": 180,
      "montant": 750
    },
    {
      "g": 181,
      "montant": 1300
    },
    {
      "g": 182,
      "montant": 1300
    },
    {
      "g": 183,
      "montant": 1300
    },
    {
      "g": 184,
      "montant": 1300
    },
    {
      "g": 185,
      "montant": 1300
    },
    {
      "g": 186,
      "montant": 1300
    },
    {
      "g": 187,
      "montant": 1300
    },
    {
      "g": 188,
      "montant": 1300
    },
    {
      "g": 189,
      "montant": 1300
    },
    {
      "g": 190,
      "montant": 1300
    },
    {
      "g": 191,
      "montant": 2300
    }
  ],
  "2013": [
    {
      "g": 140,
      "montant": 100
    },
    {
      "g": 141,
      "montant": 300
    },
    {
      "g": 142,
      "montant": 300
    },
    {
      "g": 143,
      "montant": 300
    },
    {
      "g": 144,
      "montant": 300
    },
    {
      "g": 145,
      "montant": 300
    },
    {
      "g": 146,
      "montant": 400
    },
    {
      "g": 147,
      "montant": 400
    },
    {
      "g": 148,
      "montant": 400
    },
    {
      "g": 149,
      "montant": 400
    },
    {
      "g": 150,
      "montant": 400
    },
    {
      "g": 151,
      "montant": 1000
    },
    {
      "g": 152,
      "montant": 1000
    },
    {
      "g": 153,
      "montant": 1000
    },
    {
      "g": 154,
      "montant": 1000
    },
    {
      "g": 155,
      "montant": 1000
    },
    {
      "g": 156,
      "montant": 1500
    },
    {
      "g": 157,
      "montant": 1500
    },
    {
      "g": 158,
      "montant": 1500
    },
    {
      "g": 159,
      "montant": 1500
    },
    {
      "g": 160,
      "montant": 1500
    },
    {
      "g": 161,
      "montant": 1500
    },
    {
      "g": 162,
      "montant": 1500
    },
    {
      "g": 163,
      "montant": 1500
    },
    {
      "g": 164,
      "montant": 1500
    },
    {
      "g": 165,
      "montant": 1500
    },
    {
      "g": 166,
      "montant": 1500
    },
    {
      "g": 167,
      "montant": 1500
    },
    {
      "g": 168,
      "montant": 1500
    },
    {
      "g": 169,
      "montant": 1500
    },
    {
      "g": 170,
      "montant": 1500
    },
    {
      "g": 171,
      "montant": 1500
    },
    {
      "g": 172,
      "montant": 1500
    },
    {
      "g": 173,
      "montant": 1500
    },
    {
      "g": 174,
      "montant": 1500
    },
    {
      "g": 175,
      "montant": 1500
    },
    {
      "g": 176,
      "montant": 2000
    },
    {
      "g": 177,
      "montant": 2000
    },
    {
      "g": 178,
      "montant": 2000
    },
    {
      "g": 179,
      "montant": 2000
    },
    {
      "g": 180,
      "montant": 2000
    },
    {
      "g": 181,
      "montant": 2600
    },
    {
      "g": 182,
      "montant": 2600
    },
    {
      "g": 183,
      "montant": 2600
    },
    {
      "g": 184,
      "montant": 2600
    },
    {
      "g": 185,
      "montant": 2600
    },
    {
      "g": 186,
      "montant": 3000
    },
    {
      "g": 187,
      "montant": 3000
    },
    {
      "g": 188,
      "montant": 3000
    },
    {
      "g": 189,
      "montant": 3000
    },
    {
      "g": 190,
      "montant": 3000
    },
    {
      "g": 191,
      "montant": 5000
    },
    {
      "g": 192,
      "montant": 5000
    },
    {
      "g": 193,
      "montant": 5000
    },
    {
      "g": 194,
      "montant": 5000
    },
    {
      "g": 195,
      "montant": 5000
    },
    {
      "g": 196,
      "montant": 5000
    },
    {
      "g": 197,
      "montant": 5000
    },
    {
      "g": 198,
      "montant": 5000
    },
    {
      "g": 199,
      "montant": 5000
    },
    {
      "g": 200,
      "montant": 5000
    },
    {
      "g": 201,
      "montant": 6000
    }
  ],
  "2014": [
    {
      "g": 135,
      "montant": 150
    },
    {
      "g": 136,
      "montant": 250
    },
    {
      "g": 137,
      "montant": 250
    },
    {
      "g": 138,
      "montant": 250
    },
    {
      "g": 139,
      "montant": 250
    },
    {
      "g": 140,
      "montant": 250
    },
    {
      "g": 141,
      "montant": 500
    },
    {
      "g": 142,
      "montant": 500
    },
    {
      "g": 143,
      "montant": 500
    },
    {
      "g": 144,
      "montant": 500
    },
    {
      "g": 145,
      "montant": 500
    },
    {
      "g": 146,
      "montant": 900
    },
    {
      "g": 147,
      "montant": 900
    },
    {
      "g": 148,
      "montant": 900
    },
    {
      "g": 149,
      "montant": 900
    },
    {
      "g": 150,
      "montant": 900
    },
    {
      "g": 151,
      "montant": 1600
    },
    {
      "g": 152,
      "montant": 1600
    },
    {
      "g": 153,
      "montant": 1600
    },
    {
      "g": 154,
      "montant": 1600
    },
    {
      "g": 155,
      "montant": 1600
    },
    {
      "g": 156,
      "montant": 2200
    },
    {
      "g": 157,
      "montant": 2200
    },
    {
      "g": 158,
      "montant": 2200
    },
    {
      "g": 159,
      "montant": 2200
    },
    {
      "g": 160,
      "montant": 2200
    },
    {
      "g": 161,
      "montant": 2200
    },
    {
      "g": 162,
      "montant": 2200
    },
    {
      "g": 163,
      "montant": 2200
    },
    {
      "g": 164,
      "montant": 2200
    },
    {
      "g": 165,
      "montant": 2200
    },
    {
      "g": 166,
      "montant": 2200
    },
    {
      "g": 167,
      "montant": 2200
    },
    {
      "g": 168,
      "montant": 2200
    },
    {
      "g": 169,
      "montant": 2200
    },
    {
      "g": 170,
      "montant": 2200
    },
    {
      "g": 171,
      "montant": 2200
    },
    {
      "g": 172,
      "montant": 2200
    },
    {
      "g": 173,
      "montant": 2200
    },
    {
      "g": 174,
      "montant": 2200
    },
    {
      "g": 175,
      "montant": 2200
    },
    {
      "g": 176,
      "montant": 3000
    },
    {
      "g": 177,
      "montant": 3000
    },
    {
      "g": 178,
      "montant": 3000
    },
    {
      "g": 179,
      "montant": 3000
    },
    {
      "g": 180,
      "montant": 3000
    },
    {
      "g": 181,
      "montant": 3600
    },
    {
      "g": 182,
      "montant": 3600
    },
    {
      "g": 183,
      "montant": 3600
    },
    {
      "g": 184,
      "montant": 3600
    },
    {
      "g": 185,
      "montant": 3600
    },
    {
      "g": 186,
      "montant": 4000
    },
    {
      "g": 187,
      "montant": 4000
    },
    {
      "g": 188,
      "montant": 4000
    },
    {
      "g": 189,
      "montant": 4000
    },
    {
      "g": 190,
      "montant": 4000
    },
    {
      "g": 191,
      "montant": 6500
    },
    {
      "g": 192,
      "montant": 6500
    },
    {
      "g": 193,
      "montant": 6500
    },
    {
      "g": 194,
      "montant": 6500
    },
    {
      "g": 195,
      "montant": 6500
    },
    {
      "g": 196,
      "montant": 6500
    },
    {
      "g": 197,
      "montant": 6500
    },
    {
      "g": 198,
      "montant": 6500
    },
    {
      "g": 199,
      "montant": 6500
    },
    {
      "g": 200,
      "montant": 6500
    },
    {
      "g": 201,
      "montant": 8000
    }
  ],
  "2015": [
    {
      "g": 135,
      "montant": 150
    },
    {
      "g": 136,
      "montant": 250
    },
    {
      "g": 137,
      "montant": 250
    },
    {
      "g": 138,
      "montant": 250
    },
    {
      "g": 139,
      "montant": 250
    },
    {
      "g": 140,
      "montant": 250
    },
    {
      "g": 141,
      "montant": 500
    },
    {
      "g": 142,
      "montant": 500
    },
    {
      "g": 143,
      "montant": 500
    },
    {
      "g": 144,
      "montant": 500
    },
    {
      "g": 145,
      "montant": 500
    },
    {
      "g": 146,
      "montant": 900
    },
    {
      "g": 147,
      "montant": 900
    },
    {
      "g": 148,
      "montant": 900
    },
    {
      "g": 149,
      "montant": 900
    },
    {
      "g": 150,
      "montant": 900
    },
    {
      "g": 151,
      "montant": 1600
    },
    {
      "g": 152,
      "montant": 1600
    },
    {
      "g": 153,
      "montant": 1600
    },
    {
      "g": 154,
      "montant": 1600
    },
    {
      "g": 155,
      "montant": 1600
    },
    {
      "g": 156,
      "montant": 2200
    },
    {
      "g": 157,
      "montant": 2200
    },
    {
      "g": 158,
      "montant": 2200
    },
    {
      "g": 159,
      "montant": 2200
    },
    {
      "g": 160,
      "montant": 2200
    },
    {
      "g": 161,
      "montant": 2200
    },
    {
      "g": 162,
      "montant": 2200
    },
    {
      "g": 163,
      "montant": 2200
    },
    {
      "g": 164,
      "montant": 2200
    },
    {
      "g": 165,
      "montant": 2200
    },
    {
      "g": 166,
      "montant": 2200
    },
    {
      "g": 167,
      "montant": 2200
    },
    {
      "g": 168,
      "montant": 2200
    },
    {
      "g": 169,
      "montant": 2200
    },
    {
      "g": 170,
      "montant": 2200
    },
    {
      "g": 171,
      "montant": 2200
    },
    {
      "g": 172,
      "montant": 2200
    },
    {
      "g": 173,
      "montant": 2200
    },
    {
      "g": 174,
      "montant": 2200
    },
    {
      "g": 175,
      "montant": 2200
    },
    {
      "g": 176,
      "montant": 3000
    },
    {
      "g": 177,
      "montant": 3000
    },
    {
      "g": 178,
      "montant": 3000
    },
    {
      "g": 179,
      "montant": 3000
    },
    {
      "g": 180,
      "montant": 3000
    },
    {
      "g": 181,
      "montant": 4000
    },
    {
      "g": 182,
      "montant": 4000
    },
    {
      "g": 183,
      "montant": 4000
    },
    {
      "g": 184,
      "montant": 4000
    },
    {
      "g": 185,
      "montant": 4000
    },
    {
      "g": 186,
      "montant": 4000
    },
    {
      "g": 187,
      "montant": 4000
    },
    {
      "g": 188,
      "montant": 4000
    },
    {
      "g": 189,
      "montant": 4000
    },
    {
      "g": 190,
      "montant": 4000
    },
    {
      "g": 191,
      "montant": 6500
    },
    {
      "g": 192,
      "montant": 6500
    },
    {
      "g": 193,
      "montant": 6500
    },
    {
      "g": 194,
      "montant": 6500
    },
    {
      "g": 195,
      "montant": 6500
    },
    {
      "g": 196,
      "montant": 6500
    },
    {
      "g": 197,
      "montant": 6500
    },
    {
      "g": 198,
      "montant": 6500
    },
    {
      "g": 199,
      "montant": 6500
    },
    {
      "g": 200,
      "montant": 6500
    },
    {
      "g": 201,
      "montant": 8000
    }
  ],
  "2016": [
    {
      "g": 135,
      "montant": 150
    },
    {
      "g": 136,
      "montant": 250
    },
    {
      "g": 137,
      "montant": 250
    },
    {
      "g": 138,
      "montant": 250
    },
    {
      "g": 139,
      "montant": 250
    },
    {
      "g": 140,
      "montant": 250
    },
    {
      "g": 141,
      "montant": 500
    },
    {
      "g": 142,
      "montant": 500
    },
    {
      "g": 143,
      "montant": 500
    },
    {
      "g": 144,
      "montant": 500
    },
    {
      "g": 145,
      "montant": 500
    },
    {
      "g": 146,
      "montant": 900
    },
    {
      "g": 147,
      "montant": 900
    },
    {
      "g": 148,
      "montant": 900
    },
    {
      "g": 149,
      "montant": 900
    },
    {
      "g": 150,
      "montant": 900
    },
    {
      "g": 151,
      "montant": 1600
    },
    {
      "g": 152,
      "montant": 1600
    },
    {
      "g": 153,
      "montant": 1600
    },
    {
      "g": 154,
      "montant": 1600
    },
    {
      "g": 155,
      "montant": 1600
    },
    {
      "g": 156,
      "montant": 2200
    },
    {
      "g": 157,
      "montant": 2200
    },
    {
      "g": 158,
      "montant": 2200
    },
    {
      "g": 159,
      "montant": 2200
    },
    {
      "g": 160,
      "montant": 2200
    },
    {
      "g": 161,
      "montant": 2200
    },
    {
      "g": 162,
      "montant": 2200
    },
    {
      "g": 163,
      "montant": 2200
    },
    {
      "g": 164,
      "montant": 2200
    },
    {
      "g": 165,
      "montant": 2200
    },
    {
      "g": 166,
      "montant": 2200
    },
    {
      "g": 167,
      "montant": 2200
    },
    {
      "g": 168,
      "montant": 2200
    },
    {
      "g": 169,
      "montant": 2200
    },
    {
      "g": 170,
      "montant": 2200
    },
    {
      "g": 171,
      "montant": 2200
    },
    {
      "g": 172,
      "montant": 2200
    },
    {
      "g": 173,
      "montant": 2200
    },
    {
      "g": 174,
      "montant": 2200
    },
    {
      "g": 175,
      "montant": 2200
    },
    {
      "g": 176,
      "montant": 3000
    },
    {
      "g": 177,
      "montant": 3000
    },
    {
      "g": 178,
      "montant": 3000
    },
    {
      "g": 179,
      "montant": 3000
    },
    {
      "g": 180,
      "montant": 3000
    },
    {
      "g": 181,
      "montant": 4000
    },
    {
      "g": 182,
      "montant": 4000
    },
    {
      "g": 183,
      "montant": 4000
    },
    {
      "g": 184,
      "montant": 4000
    },
    {
      "g": 185,
      "montant": 4000
    },
    {
      "g": 186,
      "montant": 4000
    },
    {
      "g": 187,
      "montant": 4000
    },
    {
      "g": 188,
      "montant": 4000
    },
    {
      "g": 189,
      "montant": 4000
    },
    {
      "g": 190,
      "montant": 4000
    },
    {
      "g": 191,
      "montant": 6500
    },
    {
      "g": 192,
      "montant": 6500
    },
    {
      "g": 193,
      "montant": 6500
    },
    {
      "g": 194,
      "montant": 6500
    },
    {
      "g": 195,
      "montant": 6500
    },
    {
      "g": 196,
      "montant": 6500
    },
    {
      "g": 197,
      "montant": 6500
    },
    {
      "g": 198,
      "montant": 6500
    },
    {
      "g": 199,
      "montant": 6500
    },
    {
      "g": 200,
      "montant": 6500
    },
    {
      "g": 201,
      "montant": 8000
    }
  ],
  "2017": [
    {
      "g": 133,
      "montant": 140
    },
    {
      "g": 134,
      "montant": 173
    },
    {
      "g": 135,
      "montant": 210
    },
    {
      "g": 136,
      "montant": 253
    },
    {
      "g": 137,
      "montant": 300
    },
    {
      "g": 138,
      "montant": 353
    },
    {
      "g": 139,
      "montant": 410
    },
    {
      "g": 140,
      "montant": 473
    },
    {
      "g": 141,
      "montant": 540
    },
    {
      "g": 142,
      "montant": 613
    },
    {
      "g": 143,
      "montant": 690
    },
    {
      "g": 144,
      "montant": 773
    },
    {
      "g": 145,
      "montant": 860
    },
    {
      "g": 146,
      "montant": 953
    },
    {
      "g": 147,
      "montant": 1050
    },
    {
      "g": 148,
      "montant": 1153
    },
    {
      "g": 149,
      "montant": 1260
    },
    {
      "g": 150,
      "montant": 1373
    },
    {
      "g": 151,
      "montant": 1490
    },
    {
      "g": 152,
      "montant": 1613
    },
    {
      "g": 153,
      "montant": 1740
    },
    {
      "g": 154,
      "montant": 1873
    },
    {
      "g": 155,
      "montant": 2010
    },
    {
      "g": 156,
      "montant": 2153
    },
    {
      "g": 157,
      "montant": 2300
    },
    {
      "g": 158,
      "montant": 2453
    },
    {
      "g": 159,
      "montant": 2610
    },
    {
      "g": 160,
      "montant": 2773
    },
    {
      "g": 161,
      "montant": 2940
    },
    {
      "g": 162,
      "montant": 3113
    },
    {
      "g": 163,
      "montant": 3290
    },
    {
      "g": 164,
      "montant": 3473
    },
    {
      "g": 165,
      "montant": 3660
    },
    {
      "g": 166,
      "montant": 3853
    },
    {
      "g": 167,
      "montant": 4050
    },
    {
      "g": 168,
      "montant": 4253
    },
    {
      "g": 169,
      "montant": 4460
    },
    {
      "g": 170,
      "montant": 4673
    },
    {
      "g": 171,
      "montant": 4890
    },
    {
      "g": 172,
      "montant": 5113
    },
    {
      "g": 173,
      "montant": 5340
    },
    {
      "g": 174,
      "montant": 5573
    },
    {
      "g": 175,
      "montant": 5810
    },
    {
      "g": 176,
      "montant": 6053
    },
    {
      "g": 177,
      "montant": 6300
    },
    {
      "g": 178,
      "montant": 6553
    },
    {
      "g": 179,
      "montant": 6810
    },
    {
      "g": 180,
      "montant": 7073
    },
    {
      "g": 181,
      "montant": 7340
    },
    {
      "g": 182,
      "montant": 7613
    },
    {
      "g": 183,
      "montant": 7890
    },
    {
      "g": 184,
      "montant": 8173
    },
    {
      "g": 185,
      "montant": 8460
    },
    {
      "g": 186,
      "montant": 8753
    },
    {
      "g": 187,
      "montant": 9050
    },
    {
      "g": 188,
      "montant": 9353
    },
    {
      "g": 189,
      "montant": 9660
    },
    {
      "g": 190,
      "montant": 9973
    },
    {
      "g": 191,
      "montant": 10000
    }
  ],
  "2018": [
    {
      "g": 133,
      "montant": 473
    },
    {
      "g": 134,
      "montant": 540
    },
    {
      "g": 135,
      "montant": 613
    },
    {
      "g": 136,
      "montant": 690
    },
    {
      "g": 137,
      "montant": 773
    },
    {
      "g": 138,
      "montant": 860
    },
    {
      "g": 139,
      "montant": 953
    },
    {
      "g": 140,
      "montant": 1050
    },
    {
      "g": 141,
      "montant": 1153
    },
    {
      "g": 142,
      "montant": 1260
    },
    {
      "g": 143,
      "montant": 1373
    },
    {
      "g": 144,
      "montant": 1490
    },
    {
      "g": 145,
      "montant": 1613
    },
    {
      "g": 146,
      "montant": 1740
    },
    {
      "g": 147,
      "montant": 1873
    },
    {
      "g": 148,
      "montant": 2010
    },
    {
      "g": 149,
      "montant": 2153
    },
    {
      "g": 150,
      "montant": 2300
    },
    {
      "g": 151,
      "montant": 2453
    },
    {
      "g": 152,
      "montant": 2610
    },
    {
      "g": 153,
      "montant": 2773
    },
    {
      "g": 154,
      "montant": 2940
    },
    {
      "g": 155,
      "montant": 3113
    },
    {
      "g": 156,
      "montant": 3290
    },
    {
      "g": 157,
      "montant": 3473
    },
    {
      "g": 158,
      "montant": 3660
    },
    {
      "g": 159,
      "montant": 3853
    },
    {
      "g": 160,
      "montant": 4050
    },
    {
      "g": 161,
      "montant": 4253
    },
    {
      "g": 162,
      "montant": 4460
    },
    {
      "g": 163,
      "montant": 4673
    },
    {
      "g": 164,
      "montant": 4890
    },
    {
      "g": 165,
      "montant": 5113
    },
    {
      "g": 166,
      "montant": 5340
    },
    {
      "g": 167,
      "montant": 5573
    },
    {
      "g": 168,
      "montant": 5810
    },
    {
      "g": 169,
      "montant": 6053
    },
    {
      "g": 170,
      "montant": 6300
    },
    {
      "g": 171,
      "montant": 6553
    },
    {
      "g": 172,
      "montant": 6810
    },
    {
      "g": 173,
      "montant": 7073
    },
    {
      "g": 174,
      "montant": 7340
    },
    {
      "g": 175,
      "montant": 7613
    },
    {
      "g": 176,
      "montant": 7890
    },
    {
      "g": 177,
      "montant": 8173
    },
    {
      "g": 178,
      "montant": 8460
    },
    {
      "g": 179,
      "montant": 8753
    },
    {
      "g": 180,
      "montant": 9050
    },
    {
      "g": 181,
      "montant": 9973
    },
    {
      "g": 182,
      "montant": 10290
    },
    {
      "g": 183,
      "montant": 10500
    }
  ],
  "2019": [
    {
      "g": 133,
      "montant": 253
    },
    {
      "g": 134,
      "montant": 300
    },
    {
      "g": 135,
      "montant": 353
    },
    {
      "g": 136,
      "montant": 410
    },
    {
      "g": 137,
      "montant": 473
    },
    {
      "g": 138,
      "montant": 540
    },
    {
      "g": 139,
      "montant": 613
    },
    {
      "g": 140,
      "montant": 690
    },
    {
      "g": 141,
      "montant": 773
    },
    {
      "g": 142,
      "montant": 860
    },
    {
      "g": 143,
      "montant": 953
    },
    {
      "g": 144,
      "montant": 1050
    },
    {
      "g": 145,
      "montant": 1101
    },
    {
      "g": 146,
      "montant": 1153
    },
    {
      "g": 147,
      "montant": 1260
    },
    {
      "g": 148,
      "montant": 1373
    },
    {
      "g": 149,
      "montant": 1490
    },
    {
      "g": 150,
      "montant": 1613
    },
    {
      "g": 151,
      "montant": 1740
    },
    {
      "g": 152,
      "montant": 1873
    },
    {
      "g": 153,
      "montant": 2010
    },
    {
      "g": 154,
      "montant": 2300
    },
    {
      "g": 155,
      "montant": 2453
    },
    {
      "g": 156,
      "montant": 2610
    },
    {
      "g": 157,
      "montant": 2773
    },
    {
      "g": 158,
      "montant": 2940
    },
    {
      "g": 159,
      "montant": 3113
    },
    {
      "g": 160,
      "montant": 3290
    },
    {
      "g": 161,
      "montant": 3473
    },
    {
      "g": 162,
      "montant": 3660
    },
    {
      "g": 163,
      "montant": 3756
    },
    {
      "g": 164,
      "montant": 3853
    },
    {
      "g": 165,
      "montant": 4050
    },
    {
      "g": 166,
      "montant": 4253
    },
    {
      "g": 167,
      "montant": 4460
    },
    {
      "g": 168,
      "montant": 4673
    },
    {
      "g": 169,
      "montant": 4890
    },
    {
      "g": 170,
      "montant": 5113
    },
    {
      "g": 171,
      "montant": 5340
    },
    {
      "g": 172,
      "montant": 5573
    },
    {
      "g": 173,
      "montant": 5810
    },
    {
      "g": 174,
      "montant": 6053
    },
    {
      "g": 175,
      "montant": 6300
    },
    {
      "g": 176,
      "montant": 6553
    },
    {
      "g": 177,
      "montant": 6810
    },
    {
      "g": 178,
      "montant": 7073
    },
    {
      "g": 179,
      "montant": 7340
    },
    {
      "g": 180,
      "montant": 7613
    },
    {
      "g": 181,
      "montant": 7890
    },
    {
      "g": 182,
      "montant": 8173
    },
    {
      "g": 183,
      "montant": 8460
    },
    {
      "g": 184,
      "montant": 8753
    },
    {
      "g": 185,
      "montant": 9050
    },
    {
      "g": 186,
      "montant": 9353
    },
    {
      "g": 187,
      "montant": 9660
    },
    {
      "g": 188,
      "montant": 9973
    },
    {
      "g": 189,
      "montant": 10290
    },
    {
      "g": 190,
      "montant": 10500
    }
  ],
  "2020": [
    {
      "g": 138,
      "montant": 50
    },
    {
      "g": 139,
      "montant": 75
    },
    {
      "g": 140,
      "montant": 100
    },
    {
      "g": 141,
      "montant": 125
    },
    {
      "g": 142,
      "montant": 150
    },
    {
      "g": 143,
      "montant": 170
    },
    {
      "g": 144,
      "montant": 190
    },
    {
      "g": 145,
      "montant": 210
    },
    {
      "g": 146,
      "montant": 230
    },
    {
      "g": 147,
      "montant": 240
    },
    {
      "g": 148,
      "montant": 260
    },
    {
      "g": 149,
      "montant": 280
    },
    {
      "g": 150,
      "montant": 310
    },
    {
      "g": 151,
      "montant": 330
    },
    {
      "g": 152,
      "montant": 360
    },
    {
      "g": 153,
      "montant": 400
    },
    {
      "g": 154,
      "montant": 450
    },
    {
      "g": 155,
      "montant": 540
    },
    {
      "g": 156,
      "montant": 650
    },
    {
      "g": 157,
      "montant": 740
    },
    {
      "g": 158,
      "montant": 818
    },
    {
      "g": 159,
      "montant": 898
    },
    {
      "g": 160,
      "montant": 983
    },
    {
      "g": 161,
      "montant": 1074
    },
    {
      "g": 162,
      "montant": 1172
    },
    {
      "g": 163,
      "montant": 1276
    },
    {
      "g": 164,
      "montant": 1386
    },
    {
      "g": 165,
      "montant": 1504
    },
    {
      "g": 166,
      "montant": 1629
    },
    {
      "g": 167,
      "montant": 1761
    },
    {
      "g": 168,
      "montant": 1901
    },
    {
      "g": 169,
      "montant": 2049
    },
    {
      "g": 170,
      "montant": 2205
    },
    {
      "g": 171,
      "montant": 2370
    },
    {
      "g": 172,
      "montant": 2544
    },
    {
      "g": 173,
      "montant": 2726
    },
    {
      "g": 174,
      "montant": 2918
    },
    {
      "g": 175,
      "montant": 3119
    },
    {
      "g": 176,
      "montant": 3331
    },
    {
      "g": 177,
      "montant": 3552
    },
    {
      "g": 178,
      "montant": 3784
    },
    {
      "g": 179,
      "montant": 4026
    },
    {
      "g": 180,
      "montant": 4279
    },
    {
      "g": 181,
      "montant": 4543
    },
    {
      "g": 182,
      "montant": 4818
    },
    {
      "g": 183,
      "montant": 5105
    },
    {
      "g": 184,
      "montant": 5404
    },
    {
      "g": 185,
      "montant": 5715
    },
    {
      "g": 186,
      "montant": 6039
    },
    {
      "g": 187,
      "montant": 6375
    },
    {
      "g": 188,
      "montant": 6724
    },
    {
      "g": 189,
      "montant": 7086
    },
    {
      "g": 190,
      "montant": 7462
    },
    {
      "g": 191,
      "montant": 7851
    },
    {
      "g": 192,
      "montant": 8254
    },
    {
      "g": 193,
      "montant": 8671
    },
    {
      "g": 194,
      "montant": 9103
    },
    {
      "g": 195,
      "montant": 9550
    },
    {
      "g": 196,
      "montant": 10011
    },
    {
      "g": 197,
      "montant": 10488
    },
    {
      "g": 198,
      "montant": 10980
    },
    {
      "g": 199,
      "montant": 11488
    },
    {
      "g": 200,
      "montant": 12012
    },
    {
      "g": 201,
      "montant": 12552
    },
    {
      "g": 202,
      "montant": 13109
    },
    {
      "g": 203,
      "montant": 13682
    },
    {
      "g": 204,
      "montant": 14273
    },
    {
      "g": 205,
      "montant": 14881
    },
    {
      "g": 206,
      "montant": 15506
    },
    {
      "g": 207,
      "montant": 16149
    },
    {
      "g": 208,
      "montant": 16810
    },
    {
      "g": 209,
      "montant": 17490
    },
    {
      "g": 210,
      "montant": 18188
    },
    {
      "g": 211,
      "montant": 18905
    },
    {
      "g": 212,
      "montant": 19641
    },
    {
      "g": 213,
      "montant": 20000
    }
  ],
  "2021": [
    {
      "g": 128,
      "montant": 0
    },
    {
      "g": 129,
      "montant": 0
    },
    {
      "g": 130,
      "montant": 0
    },
    {
      "g": 131,
      "montant": 0
    },
    {
      "g": 132,
      "montant": 0
    },
    {
      "g": 133,
      "montant": 50
    },
    {
      "g": 134,
      "montant": 75
    },
    {
      "g": 135,
      "montant": 100
    },
    {
      "g": 136,
      "montant": 125
    },
    {
      "g": 137,
      "montant": 150
    },
    {
      "g": 138,
      "montant": 170
    },
    {
      "g": 139,
      "montant": 190
    },
    {
      "g": 140,
      "montant": 210
    },
    {
      "g": 141,
      "montant": 230
    },
    {
      "g": 142,
      "montant": 240
    },
    {
      "g": 143,
      "montant": 260
    },
    {
      "g": 144,
      "montant": 280
    },
    {
      "g": 145,
      "montant": 310
    },
    {
      "g": 146,
      "montant": 330
    },
    {
      "g": 147,
      "montant": 360
    },
    {
      "g": 148,
      "montant": 400
    },
    {
      "g": 149,
      "montant": 450
    },
    {
      "g": 150,
      "montant": 540
    },
    {
      "g": 151,
      "montant": 650
    },
    {
      "g": 152,
      "montant": 740
    },
    {
      "g": 153,
      "montant": 818
    },
    {
      "g": 154,
      "montant": 898
    },
    {
      "g": 155,
      "montant": 983
    },
    {
      "g": 156,
      "montant": 1074
    },
    {
      "g": 157,
      "montant": 1172
    },
    {
      "g": 158,
      "montant": 1276
    },
    {
      "g": 159,
      "montant": 1386
    },
    {
      "g": 160,
      "montant": 1504
    },
    {
      "g": 161,
      "montant": 1629
    },
    {
      "g": 162,
      "montant": 1761
    },
    {
      "g": 163,
      "montant": 1901
    },
    {
      "g": 164,
      "montant": 2049
    },
    {
      "g": 165,
      "montant": 2205
    },
    {
      "g": 166,
      "montant": 2370
    },
    {
      "g": 167,
      "montant": 2544
    },
    {
      "g": 168,
      "montant": 2726
    },
    {
      "g": 169,
      "montant": 2918
    },
    {
      "g": 170,
      "montant": 3119
    },
    {
      "g": 171,
      "montant": 3331
    },
    {
      "g": 172,
      "montant": 3552
    },
    {
      "g": 173,
      "montant": 3784
    },
    {
      "g": 174,
      "montant": 4026
    },
    {
      "g": 175,
      "montant": 4279
    },
    {
      "g": 176,
      "montant": 4543
    },
    {
      "g": 177,
      "montant": 4818
    },
    {
      "g": 178,
      "montant": 5105
    },
    {
      "g": 179,
      "montant": 5404
    },
    {
      "g": 180,
      "montant": 5715
    },
    {
      "g": 181,
      "montant": 6039
    },
    {
      "g": 182,
      "montant": 6375
    },
    {
      "g": 183,
      "montant": 6724
    },
    {
      "g": 184,
      "montant": 7086
    },
    {
      "g": 185,
      "montant": 7462
    },
    {
      "g": 186,
      "montant": 7851
    },
    {
      "g": 187,
      "montant": 8254
    },
    {
      "g": 188,
      "montant": 8671
    },
    {
      "g": 189,
      "montant": 9103
    },
    {
      "g": 190,
      "montant": 9550
    },
    {
      "g": 191,
      "montant": 10011
    },
    {
      "g": 192,
      "montant": 10488
    },
    {
      "g": 193,
      "montant": 10980
    },
    {
      "g": 194,
      "montant": 11488
    },
    {
      "g": 195,
      "montant": 12012
    },
    {
      "g": 196,
      "montant": 12552
    },
    {
      "g": 197,
      "montant": 13109
    },
    {
      "g": 198,
      "montant": 13682
    },
    {
      "g": 199,
      "montant": 14723
    },
    {
      "g": 200,
      "montant": 14881
    },
    {
      "g": 201,
      "montant": 15506
    },
    {
      "g": 202,
      "montant": 16149
    },
    {
      "g": 203,
      "montant": 16810
    },
    {
      "g": 204,
      "montant": 17490
    },
    {
      "g": 205,
      "montant": 18188
    },
    {
      "g": 206,
      "montant": 18905
    },
    {
      "g": 207,
      "montant": 19641
    },
    {
      "g": 208,
      "montant": 20396
    },
    {
      "g": 209,
      "montant": 21171
    },
    {
      "g": 210,
      "montant": 21966
    },
    {
      "g": 211,
      "montant": 22781
    },
    {
      "g": 212,
      "montant": 23616
    },
    {
      "g": 213,
      "montant": 24472
    },
    {
      "g": 214,
      "montant": 25349
    },
    {
      "g": 215,
      "montant": 26247
    },
    {
      "g": 216,
      "montant": 27166
    },
    {
      "g": 217,
      "montant": 28107
    },
    {
      "g": 218,
      "montant": 29070
    },
    {
      "g": 219,
      "montant": 30000
    }
  ],
  "2022": [
    {
      "g": 128,
      "montant": 50
    },
    {
      "g": 129,
      "montant": 75
    },
    {
      "g": 130,
      "montant": 100
    },
    {
      "g": 131,
      "montant": 125
    },
    {
      "g": 132,
      "montant": 150
    },
    {
      "g": 133,
      "montant": 170
    },
    {
      "g": 134,
      "montant": 190
    },
    {
      "g": 135,
      "montant": 210
    },
    {
      "g": 136,
      "montant": 230
    },
    {
      "g": 137,
      "montant": 240
    },
    {
      "g": 138,
      "montant": 260
    },
    {
      "g": 139,
      "montant": 280
    },
    {
      "g": 140,
      "montant": 310
    },
    {
      "g": 141,
      "montant": 330
    },
    {
      "g": 142,
      "montant": 360
    },
    {
      "g": 143,
      "montant": 400
    },
    {
      "g": 144,
      "montant": 450
    },
    {
      "g": 145,
      "montant": 540
    },
    {
      "g": 146,
      "montant": 650
    },
    {
      "g": 147,
      "montant": 740
    },
    {
      "g": 148,
      "montant": 818
    },
    {
      "g": 149,
      "montant": 898
    },
    {
      "g": 150,
      "montant": 983
    },
    {
      "g": 151,
      "montant": 1074
    },
    {
      "g": 152,
      "montant": 1172
    },
    {
      "g": 153,
      "montant": 1276
    },
    {
      "g": 154,
      "montant": 1386
    },
    {
      "g": 155,
      "montant": 1504
    },
    {
      "g": 156,
      "montant": 1629
    },
    {
      "g": 157,
      "montant": 1761
    },
    {
      "g": 158,
      "montant": 1901
    },
    {
      "g": 159,
      "montant": 2049
    },
    {
      "g": 160,
      "montant": 2205
    },
    {
      "g": 161,
      "montant": 2370
    },
    {
      "g": 162,
      "montant": 2544
    },
    {
      "g": 163,
      "montant": 2726
    },
    {
      "g": 164,
      "montant": 2918
    },
    {
      "g": 165,
      "montant": 3119
    },
    {
      "g": 166,
      "montant": 3331
    },
    {
      "g": 167,
      "montant": 3552
    },
    {
      "g": 168,
      "montant": 3784
    },
    {
      "g": 169,
      "montant": 4026
    },
    {
      "g": 170,
      "montant": 4279
    },
    {
      "g": 171,
      "montant": 4543
    },
    {
      "g": 172,
      "montant": 4818
    },
    {
      "g": 173,
      "montant": 5105
    },
    {
      "g": 174,
      "montant": 5404
    },
    {
      "g": 175,
      "montant": 5715
    },
    {
      "g": 176,
      "montant": 6039
    },
    {
      "g": 177,
      "montant": 6375
    },
    {
      "g": 178,
      "montant": 6724
    },
    {
      "g": 179,
      "montant": 7086
    },
    {
      "g": 180,
      "montant": 7462
    },
    {
      "g": 181,
      "montant": 7851
    },
    {
      "g": 182,
      "montant": 8254
    },
    {
      "g": 183,
      "montant": 8671
    },
    {
      "g": 184,
      "montant": 9103
    },
    {
      "g": 185,
      "montant": 9550
    },
    {
      "g": 186,
      "montant": 10011
    },
    {
      "g": 187,
      "montant": 10488
    },
    {
      "g": 188,
      "montant": 10980
    },
    {
      "g": 189,
      "montant": 11488
    },
    {
      "g": 190,
      "montant": 12012
    },
    {
      "g": 191,
      "montant": 12552
    },
    {
      "g": 192,
      "montant": 13109
    },
    {
      "g": 193,
      "montant": 13109
    },
    {
      "g": 194,
      "montant": 14273
    },
    {
      "g": 195,
      "montant": 14881
    },
    {
      "g": 196,
      "montant": 15506
    },
    {
      "g": 197,
      "montant": 16149
    },
    {
      "g": 198,
      "montant": 16810
    },
    {
      "g": 199,
      "montant": 17490
    },
    {
      "g": 200,
      "montant": 18188
    },
    {
      "g": 201,
      "montant": 18905
    },
    {
      "g": 202,
      "montant": 19641
    },
    {
      "g": 203,
      "montant": 20396
    },
    {
      "g": 204,
      "montant": 21171
    },
    {
      "g": 205,
      "montant": 21966
    },
    {
      "g": 206,
      "montant": 22781
    },
    {
      "g": 207,
      "montant": 23616
    },
    {
      "g": 208,
      "montant": 24472
    },
    {
      "g": 209,
      "montant": 25349
    },
    {
      "g": 210,
      "montant": 26247
    },
    {
      "g": 211,
      "montant": 27166
    },
    {
      "g": 212,
      "montant": 28107
    },
    {
      "g": 213,
      "montant": 29070
    },
    {
      "g": 214,
      "montant": 30056
    },
    {
      "g": 215,
      "montant": 31063
    },
    {
      "g": 216,
      "montant": 32094
    },
    {
      "g": 217,
      "montant": 33147
    },
    {
      "g": 218,
      "montant": 34224
    },
    {
      "g": 219,
      "montant": 35324
    },
    {
      "g": 220,
      "montant": 36447
    },
    {
      "g": 221,
      "montant": 37595
    },
    {
      "g": 222,
      "montant": 38767
    },
    {
      "g": 223,
      "montant": 39964
    },
    {
      "g": 224,
      "montant": 40000
    }
  ],
  "2023": [
    {
      "g": 128,
      "montant": 170
    },
    {
      "g": 129,
      "montant": 190
    },
    {
      "g": 130,
      "montant": 210
    },
    {
      "g": 131,
      "montant": 230
    },
    {
      "g": 132,
      "montant": 240
    },
    {
      "g": 133,
      "montant": 260
    },
    {
      "g": 134,
      "montant": 280
    },
    {
      "g": 135,
      "montant": 310
    },
    {
      "g": 136,
      "montant": 330
    },
    {
      "g": 137,
      "montant": 360
    },
    {
      "g": 138,
      "montant": 400
    },
    {
      "g": 139,
      "montant": 450
    },
    {
      "g": 140,
      "montant": 540
    },
    {
      "g": 141,
      "montant": 650
    },
    {
      "g": 142,
      "montant": 740
    },
    {
      "g": 143,
      "montant": 818
    },
    {
      "g": 144,
      "montant": 898
    },
    {
      "g": 145,
      "montant": 983
    },
    {
      "g": 146,
      "montant": 1074
    },
    {
      "g": 147,
      "montant": 1172
    },
    {
      "g": 148,
      "montant": 1276
    },
    {
      "g": 149,
      "montant": 1386
    },
    {
      "g": 150,
      "montant": 1504
    },
    {
      "g": 151,
      "montant": 1629
    },
    {
      "g": 152,
      "montant": 1761
    },
    {
      "g": 153,
      "montant": 1901
    },
    {
      "g": 154,
      "montant": 2049
    },
    {
      "g": 155,
      "montant": 2049
    },
    {
      "g": 156,
      "montant": 2370
    },
    {
      "g": 157,
      "montant": 2544
    },
    {
      "g": 158,
      "montant": 2726
    },
    {
      "g": 159,
      "montant": 2918
    },
    {
      "g": 160,
      "montant": 3119
    },
    {
      "g": 161,
      "montant": 3331
    },
    {
      "g": 162,
      "montant": 3552
    },
    {
      "g": 163,
      "montant": 3784
    },
    {
      "g": 164,
      "montant": 4026
    },
    {
      "g": 165,
      "montant": 4279
    },
    {
      "g": 166,
      "montant": 4543
    },
    {
      "g": 167,
      "montant": 4818
    },
    {
      "g": 168,
      "montant": 5105
    },
    {
      "g": 169,
      "montant": 5404
    },
    {
      "g": 170,
      "montant": 5715
    },
    {
      "g": 171,
      "montant": 6039
    },
    {
      "g": 172,
      "montant": 6375
    },
    {
      "g": 173,
      "montant": 6724
    },
    {
      "g": 174,
      "montant": 7086
    },
    {
      "g": 175,
      "montant": 7462
    },
    {
      "g": 176,
      "montant": 7851
    },
    {
      "g": 177,
      "montant": 8254
    },
    {
      "g": 178,
      "montant": 8671
    },
    {
      "g": 179,
      "montant": 9103
    },
    {
      "g": 180,
      "montant": 9550
    },
    {
      "g": 181,
      "montant": 10011
    },
    {
      "g": 182,
      "montant": 10488
    },
    {
      "g": 183,
      "montant": 10980
    },
    {
      "g": 184,
      "montant": 11488
    },
    {
      "g": 185,
      "montant": 12012
    },
    {
      "g": 186,
      "montant": 12552
    },
    {
      "g": 187,
      "montant": 13109
    },
    {
      "g": 188,
      "montant": 13682
    },
    {
      "g": 189,
      "montant": 14273
    },
    {
      "g": 190,
      "montant": 14881
    },
    {
      "g": 191,
      "montant": 15506
    },
    {
      "g": 192,
      "montant": 16149
    },
    {
      "g": 193,
      "montant": 16810
    },
    {
      "g": 194,
      "montant": 17490
    },
    {
      "g": 195,
      "montant": 18188
    },
    {
      "g": 196,
      "montant": 18905
    },
    {
      "g": 197,
      "montant": 19641
    },
    {
      "g": 198,
      "montant": 20396
    },
    {
      "g": 199,
      "montant": 21171
    },
    {
      "g": 200,
      "montant": 21966
    },
    {
      "g": 201,
      "montant": 22781
    },
    {
      "g": 202,
      "montant": 23616
    },
    {
      "g": 203,
      "montant": 24472
    },
    {
      "g": 204,
      "montant": 25349
    },
    {
      "g": 205,
      "montant": 26247
    },
    {
      "g": 206,
      "montant": 27166
    },
    {
      "g": 207,
      "montant": 28107
    },
    {
      "g": 208,
      "montant": 29070
    },
    {
      "g": 209,
      "montant": 30056
    },
    {
      "g": 210,
      "montant": 31063
    },
    {
      "g": 211,
      "montant": 32094
    },
    {
      "g": 212,
      "montant": 33147
    },
    {
      "g": 213,
      "montant": 34224
    },
    {
      "g": 214,
      "montant": 35324
    },
    {
      "g": 215,
      "montant": 36447
    },
    {
      "g": 216,
      "montant": 37595
    },
    {
      "g": 217,
      "montant": 38767
    },
    {
      "g": 218,
      "montant": 39964
    },
    {
      "g": 219,
      "montant": 41185
    },
    {
      "g": 220,
      "montant": 42431
    },
    {
      "g": 221,
      "montant": 43703
    },
    {
      "g": 222,
      "montant": 45000
    },
    {
      "g": 223,
      "montant": 46323
    },
    {
      "g": 224,
      "montant": 47672
    },
    {
      "g": 225,
      "montant": 49047
    },
    {
      "g": 226,
      "montant": 50000
    }
  ],
  "2024": [
    {
      "g": 128,
      "montant": 260
    },
    {
      "g": 129,
      "montant": 280
    },
    {
      "g": 130,
      "montant": 310
    },
    {
      "g": 131,
      "montant": 330
    },
    {
      "g": 132,
      "montant": 360
    },
    {
      "g": 133,
      "montant": 400
    },
    {
      "g": 134,
      "montant": 450
    },
    {
      "g": 135,
      "montant": 540
    },
    {
      "g": 136,
      "montant": 650
    },
    {
      "g": 137,
      "montant": 740
    },
    {
      "g": 138,
      "montant": 818
    },
    {
      "g": 139,
      "montant": 898
    },
    {
      "g": 140,
      "montant": 983
    },
    {
      "g": 141,
      "montant": 1074
    },
    {
      "g": 142,
      "montant": 1172
    },
    {
      "g": 143,
      "montant": 1276
    },
    {
      "g": 144,
      "montant": 1386
    },
    {
      "g": 145,
      "montant": 1504
    },
    {
      "g": 146,
      "montant": 1629
    },
    {
      "g": 147,
      "montant": 1761
    },
    {
      "g": 148,
      "montant": 1901
    },
    {
      "g": 149,
      "montant": 2049
    },
    {
      "g": 150,
      "montant": 2049
    },
    {
      "g": 151,
      "montant": 2370
    },
    {
      "g": 152,
      "montant": 2544
    },
    {
      "g": 153,
      "montant": 2726
    },
    {
      "g": 154,
      "montant": 2918
    },
    {
      "g": 155,
      "montant": 3119
    },
    {
      "g": 156,
      "montant": 3331
    },
    {
      "g": 157,
      "montant": 3552
    },
    {
      "g": 158,
      "montant": 3784
    },
    {
      "g": 159,
      "montant": 4026
    },
    {
      "g": 160,
      "montant": 4279
    },
    {
      "g": 161,
      "montant": 4543
    },
    {
      "g": 162,
      "montant": 4818
    },
    {
      "g": 163,
      "montant": 5105
    },
    {
      "g": 164,
      "montant": 5404
    },
    {
      "g": 165,
      "montant": 5715
    },
    {
      "g": 166,
      "montant": 6126
    },
    {
      "g": 167,
      "montant": 6537
    },
    {
      "g": 168,
      "montant": 7248
    },
    {
      "g": 169,
      "montant": 7959
    },
    {
      "g": 170,
      "montant": 8770
    },
    {
      "g": 171,
      "montant": 9681
    },
    {
      "g": 172,
      "montant": 10692
    },
    {
      "g": 173,
      "montant": 11803
    },
    {
      "g": 174,
      "montant": 13014
    },
    {
      "g": 175,
      "montant": 14325
    },
    {
      "g": 176,
      "montant": 15736
    },
    {
      "g": 177,
      "montant": 17247
    },
    {
      "g": 178,
      "montant": 18858
    },
    {
      "g": 179,
      "montant": 20569
    },
    {
      "g": 180,
      "montant": 22380
    },
    {
      "g": 181,
      "montant": 24291
    },
    {
      "g": 182,
      "montant": 26302
    },
    {
      "g": 183,
      "montant": 28413
    },
    {
      "g": 184,
      "montant": 30624
    },
    {
      "g": 185,
      "montant": 32935
    },
    {
      "g": 186,
      "montant": 35346
    },
    {
      "g": 187,
      "montant": 37857
    },
    {
      "g": 188,
      "montant": 40468
    },
    {
      "g": 189,
      "montant": 43179
    },
    {
      "g": 190,
      "montant": 45990
    },
    {
      "g": 191,
      "montant": 48901
    },
    {
      "g": 192,
      "montant": 51912
    },
    {
      "g": 193,
      "montant": 55023
    },
    {
      "g": 194,
      "montant": 60000
    }
  ],
  "2025": [
    {
      "g": 128,
      "montant": 400
    },
    {
      "g": 129,
      "montant": 450
    },
    {
      "g": 130,
      "montant": 540
    },
    {
      "g": 131,
      "montant": 650
    },
    {
      "g": 132,
      "montant": 740
    },
    {
      "g": 133,
      "montant": 818
    },
    {
      "g": 134,
      "montant": 898
    },
    {
      "g": 135,
      "montant": 983
    },
    {
      "g": 136,
      "montant": 1074
    },
    {
      "g": 137,
      "montant": 1172
    },
    {
      "g": 138,
      "montant": 1276
    },
    {
      "g": 139,
      "montant": 1386
    },
    {
      "g": 140,
      "montant": 1504
    },
    {
      "g": 141,
      "montant": 1629
    },
    {
      "g": 142,
      "montant": 1761
    },
    {
      "g": 143,
      "montant": 1901
    },
    {
      "g": 144,
      "montant": 2049
    },
    {
      "g": 145,
      "montant": 2205
    },
    {
      "g": 146,
      "montant": 2370
    },
    {
      "g": 147,
      "montant": 2544
    },
    {
      "g": 148,
      "montant": 2726
    },
    {
      "g": 149,
      "montant": 2918
    },
    {
      "g": 150,
      "montant": 3119
    },
    {
      "g": 151,
      "montant": 3331
    },
    {
      "g": 152,
      "montant": 3552
    },
    {
      "g": 153,
      "montant": 3784
    },
    {
      "g": 154,
      "montant": 4026
    },
    {
      "g": 155,
      "montant": 4279
    },
    {
      "g": 156,
      "montant": 4543
    },
    {
      "g": 157,
      "montant": 4818
    },
    {
      "g": 158,
      "montant": 5105
    },
    {
      "g": 159,
      "montant": 5404
    },
    {
      "g": 160,
      "montant": 5715
    },
    {
      "g": 161,
      "montant": 6126
    },
    {
      "g": 162,
      "montant": 6637
    },
    {
      "g": 163,
      "montant": 7248
    },
    {
      "g": 164,
      "montant": 7959
    },
    {
      "g": 165,
      "montant": 8770
    },
    {
      "g": 166,
      "montant": 9681
    },
    {
      "g": 167,
      "montant": 10692
    },
    {
      "g": 168,
      "montant": 11803
    },
    {
      "g": 169,
      "montant": 13014
    },
    {
      "g": 170,
      "montant": 14325
    },
    {
      "g": 171,
      "montant": 15736
    },
    {
      "g": 172,
      "montant": 17247
    },
    {
      "g": 173,
      "montant": 18858
    },
    {
      "g": 174,
      "montant": 20569
    },
    {
      "g": 175,
      "montant": 22380
    },
    {
      "g": 176,
      "montant": 24291
    },
    {
      "g": 177,
      "montant": 26302
    },
    {
      "g": 178,
      "montant": 28413
    },
    {
      "g": 179,
      "montant": 30624
    },
    {
      "g": 180,
      "montant": 32935
    },
    {
      "g": 181,
      "montant": 35346
    },
    {
      "g": 182,
      "montant": 37857
    },
    {
      "g": 183,
      "montant": 40468
    },
    {
      "g": 184,
      "montant": 43179
    },
    {
      "g": 185,
      "montant": 45990
    },
    {
      "g": 186,
      "montant": 48901
    },
    {
      "g": 187,
      "montant": 51912
    },
    {
      "g": 188,
      "montant": 55023
    },
    {
      "g": 189,
      "montant": 58134
    },
    {
      "g": 190,
      "montant": 61245
    },
    {
      "g": 191,
      "montant": 64356
    },
    {
      "g": 192,
      "montant": 67467
    },
    {
      "g": 193,
      "montant": 70000
    }
  ]
}